{
    "nav_home": "Home",
    "nav_news": "News",
    "nav_live": "Live",
    "nav_matches_today": "Today's Matches",
    "login_button": "Login",
    "logout_button": "Logout",
    "hero_title": "Welcome to Nono Yalla Koura",
    "hero_subtitle": "Your first destination to follow everything about the world of football.",
    "latest_news_title": "Latest News",
    "today_matches_title": "Today's Top Matches",
    "all_news_title": "All News",
    "live_broadcast_title": "Live Match Broadcast",
    "all_matches_title": "All Matches",
    "today_matches_with_lineups": "All of Today's Matches and Lineups",
    "languages_label": "Languages:",
    "copyright": "© 2024 Nono Yalla Koura. All rights reserved.",
    "notification_follow_success": "Notifications have been enabled for this match!",
    "notification_unfollow": "You have unfollowed the match.",
    "notification_denied": "You have blocked notifications. To enable them, please change your browser settings.",
    "notification_unsupported": "This browser does not support notifications.",
    "status_live": "Live",
    "status_halftime": "Halftime",
    "status_finished": "Finished",
    "status_not_started": "Not Started",
    "status_postponed": "Postponed",
    "status_cancelled": "Cancelled",
    "status_extra_time": "Extra Time",
    "status_penalties": "Penalties",
    "show_lineup": "Show Lineup",
    "hide_lineup": "Hide Lineup",
    "read_more": "Read More",
    "news_loading": "Loading news...",
    "news_loading_error": "Error loading news. Please try again later.",
    "lineups_title": "Lineups",
    "lineups_unavailable": "Lineup is not available for this match.",
    "lineup_for": "Lineup for",
    "substitutes": "Substitutes",
    "api_error_message": "API Error: ",
    "login_to_follow": "Please log in first to follow matches.",
    "login_with_google": "Login with Google",
    "login_prompt": "Use your Google account to access additional features like following matches.",
    "profile_title": "Profile",
    "separator_or": "OR",
    "create_new_account_prompt": "Don't have an account?",
    "create_new_account_link": "Create a new account",
    "save_article": "Save",
    "unsave_article": "Unsave",
    "login_to_save_article": "Please log in first to save articles.",
    "saved_articles_title": "Saved Articles",
    "no_saved_articles": "You have no saved articles yet.",
    "followed_matches_title": "Followed Matches",
    "no_followed_matches": "You are not following any matches yet.",
    "no_live_matches": "No live matches right now.",
    "signup_title": "Create New Account",
    "name_placeholder": "Name",
    "password_placeholder": "Password",
    "confirm_password_placeholder": "Confirm Password",
    "signup_button": "Create Account",
    "login_error": "Invalid email or password.",
    "signup_success": "Account created successfully! You can now log in.",
    "password_mismatch": "Passwords do not match.",
    "email_exists": "This email is already registered.",
    "already_have_account": "Already have an account?",
    "login_link": "Login",
    "footer_quick_links": "Quick Links",
    "footer_keywords_title": "Keywords",
    "footer_keywords_list": "Today's matches, match results, live stream, kora live, yalla shoot, Egyptian league standings, Premier league standings, Mohamed Salah goals, Al Ahly news, Zamalek news, Champions League, match schedules, live scores, highlights",
    "nav_leagues": "Leagues",
    "leagues_page_title": "Leagues List",
    "available_seasons": "Available Seasons"
}